{
    "productinfo":[
        {   
            "id": 1,
            "name": "God is good merch",
            "price": 200.00,
            "image": "https://res.cloudinary.com/dpwdowzdb/image/upload/v1707145230/gggg_ljj7gw.webp",
            "count": 1
        },
        {
            "id": 2,
            "name": "ferragamo celestina",
            "price": 4500.00,
            "image": "https://res.cloudinary.com/dpwdowzdb/image/upload/v1707145244/arno-senoner-HFE2RyC76tw-unsplash_uajris.jpg",
            "count": 1
        },
        {
            "id": 3,
            "name": "ferragamo beluci",
            "price": 5000.00,
            "image": "https://res.cloudinary.com/dpwdowzdb/image/upload/v1707145243/arno-senoner-oCXVxwTFwqE-unsplash_arytfw.jpg",
            "count": 1
        },
        {
            "id": 4,
            "name": "Aldo",
            "price": 2500.00,
            "image": "https://res.cloudinary.com/dpwdowzdb/image/upload/v1707145242/mohammad-metri-E-0ON3VGrBc-unsplash_cjh2l0.jpg",
            "count": 1
        },
        {
            "id": 5,
            "name": "ecco",
            "price": 1200.00,
            "image": "https://res.cloudinary.com/dpwdowzdb/image/upload/v1707145244/mana-akbarzadegan-Y0RB2z12F1A-unsplash_dkstgf.jpg",
            "count": 1
        },
        {
            "id": 6,
            "name": "nike temple run",
            "price": 670.00,
            "image": "https://res.cloudinary.com/dpwdowzdb/image/upload/v1707145241/domino-164_6wVEHfI-unsplash_ooumln.jpg",
            "count": 1
        },
        {
            "id": 7,
            "name": "banca monet",
            "price": 3000.00,
            "image": "https://res.cloudinary.com/dpwdowzdb/image/upload/v1707145235/emily-pottiger-Zx76sbAndc0-unsplash_cbvkua.jpg",
            "count": 1
        },
        {
            "id": 8,
            "name": "satia franca",
            "price": 2400.00,
            "image": "https://res.cloudinary.com/dpwdowzdb/image/upload/v1707145237/djordje_jovicic-l1mVJnG7a84-unsplash_zoigiu.jpg",
            "count": 1
        },
        {
            "id": 9,
            "name": "glory to God hoodie",
            "price": 200.00,
            "image": "https://res.cloudinary.com/dpwdowzdb/image/upload/v1707145230/glory_mvovh0.webp",
            "count": 1
        },
        {
            "id": 10,
            "name": "The bay hat",
            "price": 40.99,
            "image": "https://res.cloudinary.com/dpwdowzdb/image/upload/v1707214485/golden_state_stywrr.avif",
            "count": 1
        }
    ]
}

